{"ParentUid":"n7ABkj6KG","Uid":"n7ABkj6KG","Data":"github에서 private repository를 personal access token으로 접속하는 방법 #github #TIL","Order":0,"IsRoot":true,"Children":[{"ParentUid":"n7ABkj6KG","Uid":"E3jBKjYMp","Data":"`git clone https://${TOKEN}:x-oauth-basic@github.com/user/repo.git`","Order":0,"IsRoot":false,"Children":[],"Images":null,"CreateTime":"1970-01-01T09:00:00+09:00","EditTime":"1970-01-01T09:00:00+09:00"}],"Images":[],"CreateTime":"2022-01-03T16:56:02+09:00","EditTime":"1970-01-01T09:00:00+09:00"}