{"ParentUid":"t2DhXVlUM","Uid":"t2DhXVlUM","Data":"뉴메레르 #TIL #단어 #경제","Order":0,"IsRoot":true,"Children":[{"ParentUid":"t2DhXVlUM","Uid":"EhZDmU-xx","Data":"Numéraire","Order":0,"IsRoot":false,"Children":[],"Images":null,"CreateTime":"1970-01-01T09:00:00+09:00","EditTime":"1970-01-01T09:00:00+09:00"},{"ParentUid":"t2DhXVlUM","Uid":"nR39V7vEe","Data":"모든 상품의 교환 비율을 설명하기 위해, 기준이 되는 상품","Order":1,"IsRoot":false,"Children":[{"ParentUid":"nR39V7vEe","Uid":"vMu4pLfB0","Data":"금","Order":0,"IsRoot":false,"Children":[],"Images":null,"CreateTime":"1970-01-01T09:00:00+09:00","EditTime":"1970-01-01T09:00:00+09:00"},{"ParentUid":"nR39V7vEe","Uid":"tNeCojagE","Data":"미 달러","Order":1,"IsRoot":false,"Children":[],"Images":null,"CreateTime":"1970-01-01T09:00:00+09:00","EditTime":"1970-01-01T09:00:00+09:00"},{"ParentUid":"nR39V7vEe","Uid":"1uDWQmat-","Data":"기축 통화가 일종의 뉴메레르인듯","Order":2,"IsRoot":false,"Children":[],"Images":null,"CreateTime":"1970-01-01T09:00:00+09:00","EditTime":"1970-01-01T09:00:00+09:00"}],"Images":null,"CreateTime":"1970-01-01T09:00:00+09:00","EditTime":"1970-01-01T09:00:00+09:00"},{"ParentUid":"t2DhXVlUM","Uid":"Skr7XP0DH","Data":"https://en.wikipedia.org/wiki/Num%C3%A9raire #번역","Order":2,"IsRoot":false,"Children":[],"Images":null,"CreateTime":"1970-01-01T09:00:00+09:00","EditTime":"1970-01-01T09:00:00+09:00"}],"Images":[],"CreateTime":"2021-12-02T23:12:34+09:00","EditTime":"1970-01-01T09:00:00+09:00"}