{"ParentUid":"vs-2ALIkQ","Uid":"vs-2ALIkQ","Data":"`sudo usermod -aG docker $USER` #TIL #docker","Order":0,"IsRoot":true,"Children":[{"ParentUid":"vs-2ALIkQ","Uid":"4V5Ux5T_C","Data":"도커 커맨드를 sudo 없이 쓰게 하는 방법","Order":0,"IsRoot":false,"Children":[],"Images":null,"CreateTime":"1970-01-01T09:00:00+09:00","EditTime":"1970-01-01T09:00:00+09:00"},{"ParentUid":"vs-2ALIkQ","Uid":"TfUyNCnRy","Data":"usermod","Order":1,"IsRoot":false,"Children":[{"ParentUid":"TfUyNCnRy","Uid":"syEo50Sur","Data":"-a : append","Order":0,"IsRoot":false,"Children":[],"Images":null,"CreateTime":"1970-01-01T09:00:00+09:00","EditTime":"1970-01-01T09:00:00+09:00"},{"ParentUid":"TfUyNCnRy","Uid":"dQDPhxR_M","Data":"-G : add to other group","Order":1,"IsRoot":false,"Children":[],"Images":null,"CreateTime":"1970-01-01T09:00:00+09:00","EditTime":"1970-01-01T09:00:00+09:00"}],"Images":null,"CreateTime":"1970-01-01T09:00:00+09:00","EditTime":"1970-01-01T09:00:00+09:00"},{"ParentUid":"vs-2ALIkQ","Uid":"LFRboK0jE","Data":"이경우 sudo를 사용했기 때문에, user가 admin으로 되어있게 된다.","Order":2,"IsRoot":false,"Children":[{"ParentUid":"LFRboK0jE","Uid":"-SL3LdKjf","Data":"따라서 docker가 admin 그룹에 포함되게 됨","Order":0,"IsRoot":false,"Children":[],"Images":null,"CreateTime":"1970-01-01T09:00:00+09:00","EditTime":"1970-01-01T09:00:00+09:00"}],"Images":null,"CreateTime":"1970-01-01T09:00:00+09:00","EditTime":"1970-01-01T09:00:00+09:00"}],"Images":[],"CreateTime":"2021-12-01T22:39:37+09:00","EditTime":"1970-01-01T09:00:00+09:00"}